coct_sr_api_client/__init__.py
coct_sr_api_client/api_client.py
coct_sr_api_client/api_response.py
coct_sr_api_client/configuration.py
coct_sr_api_client/exceptions.py
coct_sr_api_client/py.typed
coct_sr_api_client/rest.py
coct_sr_api_client/api/__init__.py
coct_sr_api_client/api/auth_group_api.py
coct_sr_api_client/api/config_group_api.py
coct_sr_api_client/api/service_request_group_api.py
coct_sr_api_client/models/__init__.py
coct_sr_api_client/models/config_subtype_schema.py
coct_sr_api_client/models/config_type_schema.py
coct_sr_api_client/models/error_schema.py
coct_sr_api_client/models/login_schema.py
coct_sr_api_client/models/request_attribute_response_schema.py
coct_sr_api_client/models/request_attributes_lookup_schema.py
coct_sr_api_client/models/request_attributes_schema.py
coct_sr_api_client/models/session_schema.py
coct_sr_api_client-0.3.0.dist-info/METADATA
coct_sr_api_client-0.3.0.dist-info/WHEEL
coct_sr_api_client-0.3.0.dist-info/top_level.txt
coct_sr_api_client-0.3.0.dist-info/RECORD
