Metadata-Version: 2.1
Name: coct-sr-api-client
Version: 0.3.0
Summary: CCT Customer Service Requests
Home-page: UNKNOWN
Author: OpenAPI Generator community
Author-email: team@openapitools.org
License: Apache 2.0
Keywords: OpenAPI,OpenAPI-Generator,CCT Customer Service Requests
Platform: UNKNOWN
Requires-Dist: pydantic (>=2)
Requires-Dist: python-dateutil
Requires-Dist: typing-extensions (>=4.7.1)
Requires-Dist: urllib3 (<2.1.0,>=1.25.3)
